LICENSE
README.md
setup.py
mecab/__init__.py
mecab/mecab.py
mecab/pybind/_mecab/_mecab.cpp
mecab/pybind/_mecab/dictionaryinfo.cpp
mecab/pybind/_mecab/lattice.cpp
mecab/pybind/_mecab/node.cpp
mecab/pybind/_mecab/path.cpp
mecab/pybind/_mecab/tagger.cpp
python_mecab_kor.egg-info/PKG-INFO
python_mecab_kor.egg-info/SOURCES.txt
python_mecab_kor.egg-info/dependency_links.txt
python_mecab_kor.egg-info/not-zip-safe
python_mecab_kor.egg-info/top_level.txt
scripts/install_mecab_ko_dic.sh
scripts/install_requirements.sh