Metadata-Version: 2.1
Name: python-mecab-kor
Version: 1.2.8
Summary: Yet another python binding for mecab-ko
Home-page: https://github.com/hyunwoongko/python-mecab-kor
Author: Hyunwoong Ko
Author-email: gusdnd852@gmail.com
License: BSD
Keywords: mecab mecab-ko python-mecab python-mecab-ko python-mecab-kor
Classifier: Development Status :: 4 - Beta
Classifier: Intended Audience :: Science/Research
Classifier: License :: OSI Approved :: BSD License
Classifier: Natural Language :: Korean
Classifier: Programming Language :: Python :: 3
Classifier: Programming Language :: Python :: 3 :: Only
Classifier: Topic :: Text Processing
Classifier: Topic :: Text Processing :: Linguistic
Requires-Python: >=3
License-File: LICENSE
